pyhscodes/COPYRIGHT.txt
pyhscodes/__init__.py
pyhscodes/databases/hscodes.json
pyhscodes/databases/sections.json
pyhscodes/db.py
pyhscodes/py.typed
pyhscodes/tests/test_general.py
pyhscodes-2.0.3.dist-info/METADATA
pyhscodes-2.0.3.dist-info/WHEEL
pyhscodes-2.0.3.dist-info/licenses/LICENSE.txt
pyhscodes-2.0.3.dist-info/RECORD
