Metadata-Version: 2.4
Name: pyhscodes
Version: 2.0.3
Summary: Harmonized System (HS) codes from the World Customs Organization with hierarchical structure and search capabilities
License: LGPL-2.1-only
License-File: LICENSE.txt
Keywords: hs codes,harmonized system,customs,trade,tariff,classification,wco,world customs organization,EUDR,CBAM
Author: David Sigley
Author-email: david@coolset.com
Maintainer: David Sigley
Maintainer-email: david@coolset.com
Requires-Python: >=3.9
Classifier: Development Status :: 4 - Beta
Classifier: Intended Audience :: Developers
Classifier: Intended Audience :: Information Technology
Classifier: License :: OSI Approved
Classifier: License :: OSI Approved :: GNU Lesser General Public License v2 (LGPLv2)
Classifier: Operating System :: OS Independent
Classifier: Programming Language :: Python
Classifier: Programming Language :: Python :: 3
Classifier: Programming Language :: Python :: 3.9
Classifier: Programming Language :: Python :: 3.10
Classifier: Programming Language :: Python :: 3.11
Classifier: Programming Language :: Python :: 3.12
Classifier: Programming Language :: Python :: 3.13
Classifier: Programming Language :: Python :: 3.14
Classifier: Topic :: Office/Business :: Financial
Classifier: Topic :: Scientific/Engineering :: Information Analysis
Classifier: Topic :: Software Development :: Libraries :: Python Modules
Project-URL: Documentation, https://github.com/sigularusrex/pyhscodes#readme
Project-URL: Homepage, https://github.com/sigularusrex/pyhscodes
Project-URL: Repository, https://github.com/sigularusrex/pyhscodes
